_jaxbind.cpython-312-darwin.so
jaxbind/misc.py
jaxbind/custom_map.py
jaxbind/__init__.py
jaxbind/jaxbind.py
jaxbind/contrib/jaxducc0.py
jaxbind/contrib/__init__.py
jaxbind-1.3.0.dist-info/RECORD
jaxbind-1.3.0.dist-info/WHEEL
jaxbind-1.3.0.dist-info/METADATA
jaxbind-1.3.0.dist-info/licenses/LICENSE
