Metadata-Version: 2.1
Name: jaxbind
Version: 1.3.0
Summary: Bind any function written in another language to JAX with support for JVP/VJP/batching/jit compilation
Author-Email: Jakob Roth <roth@mpa-garching.mpg.de>, Martin Reinecke <martin@mpa-garching.mpg.de>, Gordian Edenhofer <gordian.edenhofer@gmail.com>
License: BSD 2-Clause License
Classifier: Development Status :: 4 - Beta
Classifier: Intended Audience :: Science/Research
Classifier: Topic :: Scientific/Engineering :: Mathematics
Classifier: Topic :: Scientific/Engineering :: Physics
Classifier: License :: OSI Approved :: BSD License
Classifier: Programming Language :: C++
Classifier: Programming Language :: Python
Project-URL: Source Code, https://github.com/NIFTy-PPL/JAXbind
Project-URL: Bug Tracker, https://github.com/NIFTy-PPL/JAXbind/issues
Project-URL: README, https://github.com/NIFTy-PPL/JAXbind/blob/main/README.md
Requires-Python: >=3.10
Requires-Dist: packaging
Requires-Dist: numpy>=1.17.0
Requires-Dist: jax>=0.5
Requires-Dist: jaxlib>=0.5
Provides-Extra: test
Requires-Dist: pytest; extra == "test"
Requires-Dist: scipy; extra == "test"
Requires-Dist: ducc0; extra == "test"
Provides-Extra: doc
Requires-Dist: sphinx; extra == "doc"
Requires-Dist: pydata-sphinx-theme; extra == "doc"
Requires-Dist: myst-parser; extra == "doc"
Requires-Dist: ipykernel; extra == "doc"
Requires-Dist: jupyterlab; extra == "doc"
Requires-Dist: notebook; extra == "doc"
Requires-Dist: jupytext; extra == "doc"
Requires-Dist: nbconvert; extra == "doc"
Requires-Dist: ducc0; extra == "doc"
Requires-Dist: scipy; extra == "doc"
Provides-Extra: all
Requires-Dist: jaxbind[doc,test]; extra == "all"
